offset/__init__.py
offset/offset.py
offset/test_offset.py
offset-0.0.2.data/scripts/offset
offset-0.0.2.dist-info/METADATA
offset-0.0.2.dist-info/WHEEL
offset-0.0.2.dist-info/top_level.txt
offset-0.0.2.dist-info/RECORD
