Metadata-Version: 2.1
Name: offset
Version: 0.0.2
Summary: To encode & decode by shift text(Symmetric encryption).
Home-page: https://github.com/Ron-Chang/offset
Author: Ron Chang
Author-email: ron.hsien.chang@gmail.com
License: MIT
Platform: UNKNOWN
Requires-Python: >=3.6
